[
  {
    "description": "",
    "elements": [
      {
        "description": "",
        "id": "login-feature;can-login-with-valid-credentials",
        "keyword": "Scenario",
        "line": 6,
        "name": "Can Login With Valid Credentials",
        "steps": [
          {
            "keyword": "Before",
            "hidden": true,
            "result": {
              "status": "passed",
              "duration": 144721500
            },
            "embeddings": [
              {
                "data": "LS0tLS0tLS0tLS0tLS0tLS0gQ2FuIExvZ2luIFdpdGggVmFsaWQgQ3JlZGVudGlhbHMgaXMgc3RhcnRlZC4uLi4uLi4uLi4uLi4h",
                "mime_type": "text/plain"
              }
            ]
          },
          {
            "arguments": [],
            "keyword": "Given ",
            "line": 4,
            "name": "the user is on the login page",
            "match": {
              "location": "e2etests\\tests\\steps\\loginsteps.specs.ts:9"
            },
            "result": {
              "status": "passed",
              "duration": 549341099
            }
          },
          {
            "arguments": [],
            "keyword": "When ",
            "line": 7,
            "name": "enters valid credentials",
            "match": {
              "location": "e2etests\\tests\\steps\\loginsteps.specs.ts:14"
            },
            "result": {
              "status": "passed",
              "duration": 1258640300
            }
          },
          {
            "arguments": [],
            "keyword": "Then ",
            "line": 8,
            "name": "the user is logged in",
            "match": {
              "location": "e2etests\\tests\\steps\\loginsteps.specs.ts:18"
            },
            "result": {
              "status": "passed",
              "duration": 1012003600
            },
            "embeddings": [
              {
                "data": "U21hcnRBbm5vdGF0b3I=",
                "mime_type": "text/plain"
              }
            ]
          },
          {
            "keyword": "After",
            "hidden": true,
            "result": {
              "status": "passed",
              "duration": 43159599
            }
          }
        ],
        "tags": [],
        "type": "scenario"
      },
      {
        "description": "",
        "id": "login-feature;cannot-login-with-blank-email-and-password",
        "keyword": "Scenario",
        "line": 10,
        "name": "Cannot Login With Blank Email And Password",
        "steps": [
          {
            "keyword": "Before",
            "hidden": true,
            "result": {
              "status": "passed",
              "duration": 114959499
            },
            "embeddings": [
              {
                "data": "LS0tLS0tLS0tLS0tLS0tLS0gQ2Fubm90IExvZ2luIFdpdGggQmxhbmsgRW1haWwgQW5kIFBhc3N3b3JkIGlzIHN0YXJ0ZWQuLi4uLi4uLi4uLi4uIQ==",
                "mime_type": "text/plain"
              }
            ]
          },
          {
            "arguments": [],
            "keyword": "Given ",
            "line": 4,
            "name": "the user is on the login page",
            "match": {
              "location": "e2etests\\tests\\steps\\loginsteps.specs.ts:9"
            },
            "result": {
              "status": "passed",
              "duration": 461595000
            }
          },
          {
            "arguments": [],
            "keyword": "When ",
            "line": 11,
            "name": "enters the invalid credentials \"\" and \"\"",
            "match": {
              "location": "e2etests\\tests\\steps\\loginsteps.specs.ts:23"
            },
            "result": {
              "status": "passed",
              "duration": 1177533699
            }
          },
          {
            "arguments": [],
            "keyword": "Then ",
            "line": 12,
            "name": "\"Please enter your Email Address\" message is displayed",
            "match": {
              "location": "e2etests\\tests\\steps\\loginsteps.specs.ts:32"
            },
            "result": {
              "status": "passed",
              "duration": 8673700
            }
          },
          {
            "arguments": [],
            "keyword": "And ",
            "line": 13,
            "name": "\"Please enter your password\" message is displayed",
            "match": {
              "location": "e2etests\\tests\\steps\\loginsteps.specs.ts:32"
            },
            "result": {
              "status": "passed",
              "duration": 4909599
            }
          },
          {
            "keyword": "After",
            "hidden": true,
            "result": {
              "status": "passed",
              "duration": 45056700
            }
          }
        ],
        "tags": [],
        "type": "scenario"
      }
    ],
    "id": "login-feature",
    "line": 1,
    "keyword": "Feature",
    "name": "Login Feature",
    "tags": [],
    "uri": "e2etests\\tests\\features\\login.feature"
  }
]